{"transport_mode":"TRAIN","length":23,"width":2,"door_max":15,"parts":[{"name":"sidenew","stage":"EXTERIOR","mirror":false,"skip_rendering_if_too_far":false,"door_offset":"NONE","render_condition":"ALL","positions":[[0.0,0.0]],"whitelisted_cars":"%1,-1","blacklisted_cars":"1,-1"},{"name":"jibungbong","stage":"EXTERIOR","mirror":false,"skip_rendering_if_too_far":false,"door_offset":"NONE","render_condition":"ALL","positions":[[0.0,0.0]],"whitelisted_cars":"%1,-1","blacklisted_cars":"1,-1"},{"name":"sideunder","stage":"EXTERIOR","mirror":false,"skip_rendering_if_too_far":false,"door_offset":"NONE","render_condition":"ALL","positions":[[0.0,0.0]],"whitelisted_cars":"%1,-1","blacklisted_cars":"1,-1"},{"name":"backdoor","stage":"EXTERIOR","mirror":false,"skip_rendering_if_too_far":false,"door_offset":"NONE","render_condition":"ALL","positions":[[0.0,0.0]],"whitelisted_cars":"%1,-1","blacklisted_cars":"1,-1"},{"name":"back","stage":"EXTERIOR","mirror":false,"skip_rendering_if_too_far":false,"door_offset":"NONE","render_condition":"ALL","positions":[[0.0,0.0]],"whitelisted_cars":"%1,-1","blacklisted_cars":"1,-1"},{"name":"DT71","stage":"EXTERIOR","mirror":false,"skip_rendering_if_too_far":false,"door_offset":"NONE","render_condition":"ALL","positions":[[0.0,0.0]],"whitelisted_cars":"%1,-1","blacklisted_cars":"1,-1"},{"name":"backin","stage":"INTERIOR","mirror":false,"skip_rendering_if_too_far":false,"door_offset":"NONE","render_condition":"ALL","positions":[[0.0,0.0]],"whitelisted_cars":"%1,-1","blacklisted_cars":"1,-1"},{"name":"inside","stage":"INTERIOR","mirror":false,"skip_rendering_if_too_far":false,"door_offset":"NONE","render_condition":"ALL","positions":[[0.0,0.0]],"whitelisted_cars":"%1,-1","blacklisted_cars":"1,-1"},{"name":"seonban2","stage":"INTERIOR","mirror":false,"skip_rendering_if_too_far":false,"door_offset":"NONE","render_condition":"ALL","positions":[[0.0,0.0]],"whitelisted_cars":"%1,-1","blacklisted_cars":"1,-1"},{"name":"mak","stage":"EXTERIOR","mirror":false,"skip_rendering_if_too_far":false,"door_offset":"NONE","render_condition":"ALL","positions":[[0.0,0.0]],"whitelisted_cars":"%1,-1","blacklisted_cars":"1,-1"},{"name":"chairs","stage":"INTERIOR","mirror":false,"skip_rendering_if_too_far":false,"door_offset":"NONE","render_condition":"ALL","positions":[[0.0,0.0]],"whitelisted_cars":"%1,-1","blacklisted_cars":"1,-1"},{"name":"step","stage":"EXTERIOR","mirror":false,"skip_rendering_if_too_far":false,"door_offset":"NONE","render_condition":"ALL","positions":[[0.0,0.0]],"whitelisted_cars":"%1,-1","blacklisted_cars":"1,-1"},{"name":"habu","stage":"EXTERIOR","mirror":false,"skip_rendering_if_too_far":false,"door_offset":"NONE","render_condition":"ALL","positions":[[0.0,0.0]],"whitelisted_cars":"%1,-1","blacklisted_cars":"1,-1"},{"name":"jibung","stage":"EXTERIOR","mirror":false,"skip_rendering_if_too_far":false,"door_offset":"NONE","render_condition":"ALL","positions":[[0.0,0.0]],"whitelisted_cars":"%1,-1","blacklisted_cars":"1,-1"},{"name":"badak","stage":"INTERIOR","mirror":false,"skip_rendering_if_too_far":false,"door_offset":"NONE","render_condition":"ALL","positions":[[0.0,0.0]],"whitelisted_cars":"%1,-1","blacklisted_cars":"1,-1"},{"name":"wall","stage":"INTERIOR","mirror":false,"skip_rendering_if_too_far":false,"door_offset":"NONE","render_condition":"ALL","positions":[[0.0,0.0]],"whitelisted_cars":"%1,-1","blacklisted_cars":"1,-1"},{"name":"cheonjang","stage":"INTERIOR","mirror":false,"skip_rendering_if_too_far":false,"door_offset":"NONE","render_condition":"ALL","positions":[[0.0,0.0]],"whitelisted_cars":"%1,-1","blacklisted_cars":"1,-1"},{"name":"door_LF","stage":"EXTERIOR","mirror":false,"skip_rendering_if_too_far":false,"door_offset":"LEFT_NEGATIVE","render_condition":"ALL","positions":[[0.0,0.0]],"whitelisted_cars":"%1,-1","blacklisted_cars":"1,-1"},{"name":"door_LB","stage":"EXTERIOR","mirror":false,"skip_rendering_if_too_far":false,"door_offset":"LEFT_POSITIVE","render_condition":"ALL","positions":[[0.0,0.0]],"whitelisted_cars":"%1,-1","blacklisted_cars":"1,-1"},{"name":"door_RF","stage":"EXTERIOR","mirror":false,"skip_rendering_if_too_far":false,"door_offset":"RIGHT_NEGATIVE","render_condition":"ALL","positions":[[0.0,0.0]],"whitelisted_cars":"%1,-1","blacklisted_cars":"1,-1"},{"name":"door_RB","stage":"EXTERIOR","mirror":false,"skip_rendering_if_too_far":false,"door_offset":"RIGHT_POSITIVE","render_condition":"ALL","positions":[[0.0,0.0]],"whitelisted_cars":"%1,-1","blacklisted_cars":"1,-1"},
{"name":"loco_badak","stage":"INTERIOR","mirror":false,"skip_rendering_if_too_far":false,"door_offset":"NONE","render_condition":"ALL","positions":[[0.0,0.0]],"whitelisted_cars":"1,-1","blacklisted_cars":"%1,-1"},{"name":"loco_fronthabu","stage":"EXTERIOR","mirror":false,"skip_rendering_if_too_far":false,"door_offset":"NONE","render_condition":"ALL","positions":[[0.0,0.0]],"whitelisted_cars":"1,-1","blacklisted_cars":"%1,-1"},{"name":"loco_side","stage":"EXTERIOR","mirror":false,"skip_rendering_if_too_far":false,"door_offset":"NONE","render_condition":"ALL","positions":[[0.0,0.0]],"whitelisted_cars":"1,-1","blacklisted_cars":"%1,-1"},{"name":"loco_habu","stage":"EXTERIOR","mirror":false,"skip_rendering_if_too_far":false,"door_offset":"NONE","render_condition":"ALL","positions":[[0.0,0.0]],"whitelisted_cars":"1,-1","blacklisted_cars":"%1,-1"},{"name":"loco_bogie","stage":"EXTERIOR","mirror":false,"skip_rendering_if_too_far":false,"door_offset":"NONE","render_condition":"ALL","positions":[[0.0,0.0]],"whitelisted_cars":"1,-1","blacklisted_cars":"%1,-1"},{"name":"loco_intercity","stage":"EXTERIOR","mirror":false,"skip_rendering_if_too_far":false,"door_offset":"NONE","render_condition":"ALL","positions":[[0.0,0.0]],"whitelisted_cars":"1,-1","blacklisted_cars":"%1,-1"},{"name":"loco_front","stage":"EXTERIOR","mirror":false,"skip_rendering_if_too_far":false,"door_offset":"NONE","render_condition":"ALL","positions":[[0.0,0.0]],"whitelisted_cars":"1,-1","blacklisted_cars":"%1,-1"},{"name":"loco_light","stage":"LIGHTS","mirror":false,"skip_rendering_if_too_far":false,"door_offset":"NONE","render_condition":"ALL","positions":[[0.0,0.0]],"whitelisted_cars":"1,-1","blacklisted_cars":"%1,-1"},{"name":"loco_backdoor","stage":"EXTERIOR","mirror":false,"skip_rendering_if_too_far":false,"door_offset":"NONE","render_condition":"ALL","positions":[[0.0,0.0]],"whitelisted_cars":"1,-1","blacklisted_cars":"%1,-1"},{"name":"loco_back","stage":"EXTERIOR","mirror":false,"skip_rendering_if_too_far":false,"door_offset":"NONE","render_condition":"ALL","positions":[[0.0,0.0]],"whitelisted_cars":"1,-1","blacklisted_cars":"%1,-1"},{"name":"loco_bong","stage":"EXTERIOR","mirror":false,"skip_rendering_if_too_far":false,"door_offset":"NONE","render_condition":"ALL","positions":[[0.0,0.0]],"whitelisted_cars":"1,-1","blacklisted_cars":"%1,-1"},{"name":"loco_mak","stage":"EXTERIOR","mirror":false,"skip_rendering_if_too_far":false,"door_offset":"NONE","render_condition":"ALL","positions":[[0.0,0.0]],"whitelisted_cars":"1,-1","blacklisted_cars":"%1,-1"},{"name":"loco_dashboard","stage":"INTERIOR","mirror":false,"skip_rendering_if_too_far":false,"door_offset":"NONE","render_condition":"ALL","positions":[[0.0,0.0]],"whitelisted_cars":"1,-1","blacklisted_cars":"%1,-1"},{"name":"loco_jibung","stage":"EXTERIOR","mirror":false,"skip_rendering_if_too_far":false,"door_offset":"NONE","render_condition":"ALL","positions":[[0.0,0.0]],"whitelisted_cars":"1,-1","blacklisted_cars":"%1,-1"},{"name":"loco_cheonjang","stage":"INTERIOR","mirror":false,"skip_rendering_if_too_far":false,"door_offset":"NONE","render_condition":"ALL","positions":[[0.0,0.0]],"whitelisted_cars":"1,-1","blacklisted_cars":"%1,-1"},{"name":"loco_wiper","stage":"EXTERIOR","mirror":false,"skip_rendering_if_too_far":false,"door_offset":"NONE","render_condition":"ALL","positions":[[0.0,0.0]],"whitelisted_cars":"1,-1","blacklisted_cars":"%1,-1"},{"name":"loco_windowteul","stage":"EXTERIOR","mirror":false,"skip_rendering_if_too_far":false,"door_offset":"NONE","render_condition":"ALL","positions":[[0.0,0.0]],"whitelisted_cars":"1,-1","blacklisted_cars":"%1,-1"},{"name":"loco_aircon","stage":"EXTERIOR","mirror":false,"skip_rendering_if_too_far":false,"door_offset":"NONE","render_condition":"ALL","positions":[[0.0,0.0]],"whitelisted_cars":"1,-1","blacklisted_cars":"%1,-1"},{"name":"loco_frontside","stage":"EXTERIOR","mirror":false,"skip_rendering_if_too_far":false,"door_offset":"NONE","render_condition":"ALL","positions":[[0.0,0.0]],"whitelisted_cars":"1,-1","blacklisted_cars":"%1,-1"},{"name":"loco_wallout","stage":"EXTERIOR","mirror":false,"skip_rendering_if_too_far":false,"door_offset":"NONE","render_condition":"ALL","positions":[[0.0,0.0]],"whitelisted_cars":"1,-1","blacklisted_cars":"%1,-1"}]}